{
  "runtimeOptions": {
    "tfm": "net6.0",
    "frameworks": [
      {
        "name": "Microsoft.NETCore.App",
        "version": "6.0.0"
      },
      {
        "name": "Microsoft.WindowsDesktop.App",
        "version": "6.0.0"
      }
    ],
    "additionalProbingPaths": [
      "C:\\Users\\admin\\.dotnet\\store\\|arch|\\|tfm|",
      "C:\\Users\\admin\\.nuget\\packages",
      "C:\\Program Files (x86)\\DevExpress 20.2\\Components\\Offline Packages",
      "C:\\Program Files (x86)\\DevExpress 21.1\\Components\\Offline Packages",
      "C:\\Program Files\\dotnet\\sdk\\NuGetFallbackFolder"
    ],
    "configProperties": {
      "Microsoft.NETCore.DotNetHostPolicy.SetAppPaths": true
    }
  }
}